{"cameraMode":{"drawMode":0,"name":"Shaded","section":"Shading Mode"},"sceneLighting":true,"audioPlay":false,"sceneViewState":{"m_AlwaysRefresh":false,"showFog":true,"showSkybox":true,"showFlares":true,"showImageEffects":true,"showParticleSystems":true,"showVisualEffectGraphs":true,"m_FxEnabled":true},"in2DMode":false,"pivot":{"x":10.732451438903809,"y":4.342480659484863,"z":-70.04779052734375},"rotation":{"x":-0.02680971845984459,"y":-0.7305301427841187,"z":0.028736528009176256,"w":-0.6817831993103027},"size":18.26355743408203,"orthographic":false}